README.rst
setup.cfg
setup.py
ce_api/__init__.py
ce_api/api_client.py
ce_api/configuration.py
ce_api/legacy_setup.py
ce_api/login_example.py
ce_api/rest.py
ce_api/api/__init__.py
ce_api/api/backends_api.py
ce_api/api/billing_api.py
ce_api/api/datasources_api.py
ce_api/api/default_api.py
ce_api/api/evaluate_api.py
ce_api/api/functions_api.py
ce_api/api/login_api.py
ce_api/api/metrics_api.py
ce_api/api/orchestrators_api.py
ce_api/api/organizations_api.py
ce_api/api/pipelines_api.py
ce_api/api/providers_api.py
ce_api/api/users_api.py
ce_api/api/workspaces_api.py
ce_api/models/__init__.py
ce_api/models/artifact.py
ce_api/models/auth_email.py
ce_api/models/backend.py
ce_api/models/backend_create.py
ce_api/models/billing.py
ce_api/models/body_create_user_open_api_v1_users_open_post.py
ce_api/models/body_login_access_token_api_v1_login_access_token_post.py
ce_api/models/body_update_loggedin_user_api_v1_users_put.py
ce_api/models/body_update_user_me_api_v1_users_me_put.py
ce_api/models/component_metric.py
ce_api/models/component_status.py
ce_api/models/datasource.py
ce_api/models/datasource_bq.py
ce_api/models/datasource_bq_create.py
ce_api/models/datasource_commit.py
ce_api/models/datasource_commit_create.py
ce_api/models/datasource_commit_in_db.py
ce_api/models/datasource_create.py
ce_api/models/datasource_image_create.py
ce_api/models/datasource_image_in_db.py
ce_api/models/datasource_in_db.py
ce_api/models/function.py
ce_api/models/function_create.py
ce_api/models/function_in_db.py
ce_api/models/function_version.py
ce_api/models/function_version_base_in_db.py
ce_api/models/function_version_create.py
ce_api/models/function_version_create_api_helper.py
ce_api/models/function_version_get_api_helper.py
ce_api/models/function_version_in_db.py
ce_api/models/http_validation_error.py
ce_api/models/invite.py
ce_api/models/invite_create.py
ce_api/models/metric_info.py
ce_api/models/orchestrator.py
ce_api/models/orchestrator_create.py
ce_api/models/organization.py
cengine.egg-info/PKG-INFO
cengine.egg-info/SOURCES.txt
cengine.egg-info/dependency_links.txt
cengine.egg-info/entry_points.txt
cengine.egg-info/requires.txt
cengine.egg-info/top_level.txt
