Metadata-Version: 1.2
Name: cengine
Version: 0.20.1
Summary: This is the maiot Core Engine.
Home-page: https://docs.maiot.io/
Author: maiot GmbH
Author-email: support@maiot.io
License: Apache License 2.0
Keywords: deep,learning,production,machine,pipeline
Platform: UNKNOWN
Classifier: Development Status :: 4 - Beta
Classifier: Intended Audience :: Developers
Classifier: Topic :: Software Development :: Libraries
Classifier: License :: OSI Approved :: Apache Software License
Classifier: Programming Language :: Python :: 3.7
Requires-Python: >=3.5.*
